LICENSE
epub_image_optimizer/__init__.py
epub_image_optimizer/__main__.py
epub_image_optimizer/cli.py
epub_image_optimizer/image_optimizer.py
epub_image_optimizer/progress_bar.py
epub_image_optimizer-1.1.2.dist-info/LICENSE
epub_image_optimizer-1.1.2.dist-info/METADATA
epub_image_optimizer-1.1.2.dist-info/WHEEL
epub_image_optimizer-1.1.2.dist-info/entry_points.txt
epub_image_optimizer-1.1.2.dist-info/RECORD
