Metadata-Version: 2.1
Name: epub-image-optimizer
Version: 1.1.2
Summary: Small application to optimize images (and cover) inside epub files
Home-page: https://github.com/Jabbo16/epub-image-optimizer
License: MIT
Keywords: epub,image,optimizer,cli,tinify
Author: Javier Sacido
Author-email: jabbo16@gmail.com
Requires-Python: >=3.8,<4.0
Classifier: Development Status :: 5 - Production/Stable
Classifier: Environment :: Console
Classifier: Intended Audience :: End Users/Desktop
Classifier: License :: OSI Approved :: MIT License
Classifier: Operating System :: OS Independent
Classifier: Programming Language :: Python :: 3
Classifier: Programming Language :: Python :: 3.8
Classifier: Programming Language :: Python :: 3.9
Classifier: Programming Language :: Python :: 3.10
Classifier: Programming Language :: Python :: 3.11
Classifier: Programming Language :: Python :: 3.12
Classifier: Programming Language :: Python :: 3 :: Only
Classifier: Topic :: Utilities
Requires-Dist: Pillow (==10.2.0)
Requires-Dist: click (>=8.0.1,<9.0.0)
Requires-Dist: coloredlogs (>=15.0.1,<16.0.0)
Requires-Dist: defusedxml (>=0.7.1,<0.8.0)
Requires-Dist: lxml (>=4.6.3,<6.0.0)
Requires-Dist: rich (>=11,<14)
Requires-Dist: tinify (==1.6.0)
Project-URL: Repository, https://github.com/Jabbo16/epub-image-optimizer
